balaganagent/__init__.py
balaganagent/cli.py
balaganagent/engine.py
balaganagent/experiment.py
balaganagent/reporting.py
balaganagent/runner.py
balaganagent/verbose.py
balaganagent/wrapper.py
balaganagent/hooks/__init__.py
balaganagent/hooks/chaos_hooks.py
balaganagent/injectors/__init__.py
balaganagent/injectors/base.py
balaganagent/injectors/budget.py
balaganagent/injectors/context.py
balaganagent/injectors/delay.py
balaganagent/injectors/hallucination.py
balaganagent/injectors/tool_failure.py
balaganagent/metrics/__init__.py
balaganagent/metrics/collector.py
balaganagent/metrics/mttr.py
balaganagent/metrics/recovery.py
balaganagent/metrics/reliability.py
balaganagent/wrappers/__init__.py
balaganagent/wrappers/autogen.py
balaganagent/wrappers/claude_sdk.py
balaganagent/wrappers/claude_sdk_client.py
balaganagent/wrappers/claude_sdk_hooks.py
balaganagent/wrappers/crewai.py
balaganagent/wrappers/langchain.py
balagan_agent-0.4.0.dist-info/METADATA
balagan_agent-0.4.0.dist-info/WHEEL
balagan_agent-0.4.0.dist-info/entry_points.txt
balagan_agent-0.4.0.dist-info/licenses/LICENSE
balagan_agent-0.4.0.dist-info/RECORD
