Metadata-Version: 2.4
Name: balagan-agent
Version: 0.4.0
Summary: Chaos engineering framework for AI agents - stress-test agent reliability
Project-URL: Homepage, https://github.com/arielshad/balagan-agent
Project-URL: Documentation, https://github.com/arielshad/balagan-agent#readme
Project-URL: Repository, https://github.com/arielshad/balagan-agent
Project-URL: Issues, https://github.com/arielshad/balagan-agent/issues
Author: Ariel Shadkhan
License-Expression: Apache-2.0
License-File: LICENSE
Keywords: agents,ai,chaos-engineering,llm,reliability,stress-testing,testing
Classifier: Development Status :: 3 - Alpha
Classifier: Intended Audience :: Developers
Classifier: License :: OSI Approved :: Apache Software License
Classifier: Programming Language :: Python :: 3
Classifier: Programming Language :: Python :: 3.10
Classifier: Programming Language :: Python :: 3.11
Classifier: Programming Language :: Python :: 3.12
Classifier: Topic :: Scientific/Engineering :: Artificial Intelligence
Classifier: Topic :: Software Development :: Testing
Requires-Python: >=3.10
Requires-Dist: claude-agent-sdk>=0.1.0
Requires-Dist: python-dotenv>=1.0.0
Provides-Extra: all-wrappers
Requires-Dist: crewai>=0.28.0; extra == 'all-wrappers'
Requires-Dist: langchain-core>=0.1.0; extra == 'all-wrappers'
Requires-Dist: langchain-google-genai>=2.0.0; extra == 'all-wrappers'
Requires-Dist: langchain>=0.1.0; extra == 'all-wrappers'
Requires-Dist: pyautogen>=0.2.0; extra == 'all-wrappers'
Requires-Dist: python-dotenv>=1.0.0; extra == 'all-wrappers'
Provides-Extra: autogen
Requires-Dist: pyautogen>=0.2.0; extra == 'autogen'
Provides-Extra: claude-agent-sdk
Requires-Dist: claude-agent-sdk>=0.1.0; extra == 'claude-agent-sdk'
Provides-Extra: crewai
Requires-Dist: crewai>=0.28.0; extra == 'crewai'
Provides-Extra: crewai-gemini
Requires-Dist: crewai>=0.28.0; extra == 'crewai-gemini'
Requires-Dist: langchain-google-genai>=2.0.0; extra == 'crewai-gemini'
Requires-Dist: python-dotenv>=1.0.0; extra == 'crewai-gemini'
Provides-Extra: dev
Requires-Dist: black>=23.0; extra == 'dev'
Requires-Dist: mypy>=1.0; extra == 'dev'
Requires-Dist: pytest-asyncio>=0.21; extra == 'dev'
Requires-Dist: pytest-bdd>=7.0; extra == 'dev'
Requires-Dist: pytest-cov>=4.0; extra == 'dev'
Requires-Dist: pytest>=7.0; extra == 'dev'
Requires-Dist: python-semantic-release>=9.0.0; extra == 'dev'
Requires-Dist: ruff>=0.1; extra == 'dev'
Provides-Extra: langchain
Requires-Dist: langchain-core>=0.1.0; extra == 'langchain'
Requires-Dist: langchain>=0.1.0; extra == 'langchain'
